{
    "id": "twilight",
    "name": "Twilight Imperium",
    "description": "Twilight Imperium 4th Edition galaxy generator",
    "flat": true,
    "fixedLayout": true,
    "players": [3, 4, 5, 6, 7, 8],
    "defaultPlayers": 6,
    "tileTypes": ["blue", "red", "green", "lanes", "legends", "rex"],
    "colors": {
        "rex": "#FFD700",
        "blue": "#1565C0",
        "red": "#C62828",
        "green": "#2E7D32",
        "lanes": "#37474F",
        "legends": "#FF8F00"
    },
    "layout": {
        "R0": { "q": 0, "r": 0, "type": "rex", "label": "Rex" },
        "R1D1": { "q": 0, "r": 1, "type": "red" },
        "R1D2": { "q": 1, "r": 1, "type": "red" },
        "R1D3": { "q": 1, "r": 0, "type": "red" },
        "R1D4": { "q": 0, "r": -1, "type": "red" },
        "R1D5": { "q": -1, "r": 0, "type": "red" },
        "R1D6": { "q": -1, "r": 1, "type": "red" },
        "R2D1": { "q": 0, "r": 2, "type": "lanes" },
        "R2D2": { "q": 1, "r": 2, "type": "blue" },
        "R2D3": { "q": 2, "r": 1, "type": "lanes" },
        "R2D4": { "q": 2, "r": 0, "type": "blue" },
        "R2D5": { "q": 2, "r": -1, "type": "lanes" },
        "R2D6": { "q": 1, "r": -1, "type": "blue" },
        "R2D7": { "q": 0, "r": -2, "type": "lanes" },
        "R2D8": { "q": -1, "r": -1, "type": "blue" },
        "R2D9": { "q": -2, "r": -1, "type": "lanes" },
        "R2D10": { "q": -2, "r": 0, "type": "blue" },
        "R2D11": { "q": -2, "r": 1, "type": "lanes" },
        "R2D12": { "q": -1, "r": 2, "type": "blue" },
        "R3D1": { "q": 0, "r": 3, "type": "green" },
        "R3D2": { "q": 1, "r": 3, "type": "blue" },
        "R3D3": { "q": 2, "r": 2, "type": "red" },
        "R3D4": { "q": 3, "r": 2, "type": "green" },
        "R3D5": { "q": 3, "r": 1, "type": "blue" },
        "R3D6": { "q": 3, "r": 0, "type": "red" },
        "R3D7": { "q": 3, "r": -1, "type": "green" },
        "R3D8": { "q": 2, "r": -2, "type": "blue" },
        "R3D9": { "q": 1, "r": -2, "type": "red" },
        "R3D10": { "q": 0, "r": -3, "type": "green" },
        "R3D11": { "q": -1, "r": -2, "type": "blue" },
        "R3D12": { "q": -2, "r": -2, "type": "red" },
        "R3D13": { "q": -3, "r": -1, "type": "green" },
        "R3D14": { "q": -3, "r": 0, "type": "blue" },
        "R3D15": { "q": -3, "r": 1, "type": "red" },
        "R3D16": { "q": -3, "r": 2, "type": "green" },
        "R3D17": { "q": -2, "r": 2, "type": "blue" },
        "R3D18": { "q": -1, "r": 3, "type": "red" }
    }
}
